{
  "name": "仮身サンプル",
  "relationship": [],
  "makeDate": "2025-10-13T00:00:00Z",
  "updateDate": "2026-01-02T00:39:59.535Z",
  "accessDate": "2026-01-02T00:39:44.081Z",
  "periodDate": null,
  "refCount": 1,
  "editable": true,
  "readable": true,
  "maker": "TADjs User",
  "window": {
    "pos": {
      "x": 0,
      "y": 227
    },
    "width": 734,
    "height": 448,
    "minWidth": 200,
    "minHeight": 200,
    "resizable": true,
    "scrollable": true,
    "maximize": false,
    "maximizable": true,
    "minimizable": true,
    "closable": true,
    "alwaysOnTop": false,
    "skipTaskbar": false,
    "frame": true,
    "transparent": false,
    "backgroundColor": "#f3ffff",
    "scrollPos": {
      "x": 0,
      "y": 0
    }
  },
  "applist": {
    "virtual-object-list": {
      "name": "仮身一覧",
      "defaultOpen": true
    },
    "basic-figure-editor": {
      "name": "基本図形編集",
      "defaultOpen": false
    }
  }
}